ifCNV
