Metadata-Version: 2.1
Name: ifCNV
Version: 0.2.1
Summary: ifCNV
Home-page: https://github.com/SimCab-CHU/ifCNV
Author: Simon Cabello
Author-email: s-cabelloaguilar@chu-montpellier.fr
License: UNKNOWN
Project-URL: Bug Reports, https://github.com/SimCab-CHU/ifCNV/issues
Project-URL: Source, https://github.com/SimCab-CHU/ifCNV
Platform: UNKNOWN
Classifier: Programming Language :: Python :: 3
Classifier: Operating System :: MacOS :: MacOS X
Classifier: Operating System :: POSIX :: Linux
Classifier: Development Status :: 5 - Production/Stable
Classifier: Programming Language :: Python :: Implementation :: PyPy
Classifier: Topic :: Scientific/Engineering :: Bio-Informatics
Classifier: Topic :: Scientific/Engineering :: Artificial Intelligence
Classifier: License :: OSI Approved :: GNU General Public License v3 (GPLv3)
License-File: LICENSE.txt
